milindustry/__init__.py
milindustry/admin.py
milindustry/app_settings.py
milindustry/apps.py
milindustry/auth_hooks.py
milindustry/helpers.py
milindustry/providers.py
milindustry/signals.py
milindustry/tasks.py
milindustry/urls.py
milindustry/dataclasses/industry_job.py
milindustry/dataclasses/slots_overview.py
milindustry/locale/.gitkeep
milindustry/management/commands/__init__.py
milindustry/management/commands/milindustry_load_data.py
milindustry/migrations/0001_initial.py
milindustry/migrations/0002_industrycharacter_industrycharacterskill_and_more.py
milindustry/migrations/0003_jobslotsusage.py
milindustry/migrations/__init__.py
milindustry/models/__init__.py
milindustry/models/general.py
milindustry/models/industry_character.py
milindustry/models/job_slots_usage.py
milindustry/services/__init__.py
milindustry/services/jobs_service.py
milindustry/static/example/.gitkeep
milindustry/templates/milindustry/base.html
milindustry/templates/milindustry/dashboard.html
milindustry/templates/milindustry/overview.html
milindustry/templatetags/__init__.py
milindustry/templatetags/custom_filters.py
milindustry/tests/__init__.py
milindustry/views/__init__.py
milindustry/views/dashboard_view.py
mil_industry-0.0.6.dist-info/licenses/LICENSE
mil_industry-0.0.6.dist-info/WHEEL
mil_industry-0.0.6.dist-info/METADATA
mil_industry-0.0.6.dist-info/RECORD
