Metadata-Version: 2.4
Name: mil-industry
Version: 0.0.6
Summary: Initialize the app
Author-email: Kevin PIERONNE <kevin.pieronne@gmail.com>
Requires-Python: >=3.8
Classifier: Environment :: Web Environment
Classifier: Framework :: Django
Classifier: Framework :: Django :: 4.0
Classifier: Framework :: Django :: 4.2
Classifier: Intended Audience :: Developers
Classifier: License :: OSI Approved :: MIT License
Classifier: Operating System :: OS Independent
Classifier: Programming Language :: Python
Classifier: Programming Language :: Python :: 3.8
Classifier: Programming Language :: Python :: 3.9
Classifier: Programming Language :: Python :: 3.10
Classifier: Programming Language :: Python :: 3.11
Classifier: Topic :: Internet :: WWW/HTTP
Classifier: Topic :: Internet :: WWW/HTTP :: Dynamic Content
License-File: LICENSE
Requires-Dist: allianceauth>=3
Project-URL: Homepage, https://gitlab.com/storm-custom-auth/mil-industry
